Metadata-Version: 2.1
Name: httpIm
Version: 1.0.0
Summary: Import files via HTTP.
Home-page: UNKNOWN
Author: Sendokame
License: UNKNOWN
Platform: UNKNOWN
